[
{ "name": "Anhui", "coordinates": [117, 31.833333] },
{ "name": "Beijing", "coordinates": [116.42, 39.9] },
{ "name": "Fujian", "coordinates": [117.85, 25.9] },
{ "name": "Guangdong", "coordinates": [113.5, 23.4] },
{ "name": "Jiangsu", "coordinates": [119.8, 32.9] },
{ "name": "Jiangxi", "coordinates": [116.0, 27.3] },
{ "name": "Hebei", "coordinates": [116.7, 39.3] },
{ "name": "Henan", "coordinates": [113.5, 33.9] },
{ "name": "Shandong", "coordinates": [118.4, 36.4] },
{ "name": "Shanghai", "coordinates": [121.6, 31.1] },
{ "name": "Zhejiang", "coordinates": [120.5, 29.2] }
]

